{
  "$schema": "http://json-schema.org/draft-07/schema#",
  "$id": "https://emc.spacebel.be/stac/schemas/eof-eos/v0.1.0/schema.json",
  "title": "Framework for Earth Observation Science Missions extension for STAC",
  "description": "Framework for Earth Observation Science Missions extension for STAC",
  "type": "object",
  "required": [
    "stac_extensions"
  ],
  "properties": {
    "stac_extensions": {
      "type": "array",
      "contains": {
        "const": "https://xxx.github.io/eof-eos-stac-extension/v0.1.0/schema.json"
      }
    }
  },
  "oneOf": [
    {
      "$comment": "This is the schema for STAC Items.",
      "allOf": [
        {
          "type": "object",
          "required": [
            "type",
            "properties",
            "assets"
          ],
          "properties": {
            "type": {
              "const": "Feature"
            },
            "properties": {
              "$ref": "#/definitions/fields"
            },
            "assets": {
              "type": "object",
              "additionalProperties": {
                "$ref": "#/definitions/fields"
              }
            }
          }
        },
        {
          "$ref": "#/definitions/stac_extensions"
        }
      ]
    },
    {
      "$comment": "This is the schema for STAC Collections.",
      "allOf": [
        {
          "type": "object",
          "required": [
            "type"
          ],
          "properties": {
            "type": {
              "const": "Collection"
            },
            "assets": {
              "type": "object",
              "additionalProperties": {
                "$ref": "#/definitions/fields"
              }
            },
            "item_assets": {
              "type": "object",
              "additionalProperties": {
                "$ref": "#/definitions/fields"
              }
            }
          }
        },
        {
          "$ref": "#/definitions/stac_extensions"
        }
      ]
    }
  ],
  "definitions": {
    "stac_extensions": {
      "type": "object",
      "required": [
        "stac_extensions"
      ],
      "properties": {
        "stac_extensions": {
          "type": "array",
          "contains": {
            "const": "https://xxx.github.io/eof-eos-stac-extension/v0.1.0/schema.json"
          }
        }
      }
    },
    "fields": {
      "type": "object",
      "properties": {
		"eof-eos:global_coverage_id": {
		  "title": "Global coverage identifier",
		   "description": "tbd",
		  "type": "string"
        },	
	    "eof-eos:mission_phase": {
		  "title": "Mission phase",
		   "description": "tbd",
		  "type": "string"
        },
        "eof-eos:major_cycle_id": {
		  "title": "Major cycle identifier",
		  "description": "tbd",
		  "type": "string"
        },
        "eof-eos:repeat_cycle_id": {
		  "title": "Repeat cycle identifier",
		  "description": "tbd",
		  "type": "string"
        },
         "eof-eos:orbit_drift_flag": {
		  "title": "Orbit drift flag",
		  "description": "tbd",
		  "type": "boolean"
        },
		"eof-eos:stack_id": {          
		  "title": "Stack identifier",
		  "description": "tbd",
		  "type": "string"
        },
		"eof-eos:is_coregistration_primary": {
		  "title": "Coregistration primary image flag",
		  "description": "tbd",
		  "type": "boolean"
        }
      },
      "patternProperties": {
        "^(?!eof-eos:)": {}
      },
      "additionalProperties": false
    }
  }
}